{
	"parent": "block/block",
	"textures": {
		"1": "block/cobblestone",
		"particle": "#0"
	},
	"elements": [
		{
			"from": [0, 0, 0],
			"to": [16, 16, 3],
			"faces": {
				"north": {"uv": [0, 0, 16, 16], "texture": "#0"},
				"east": {"uv": [13, 0, 16, 16], "texture": "#0"},
				"south": {"uv": [0, 0, 16, 16], "texture": "#0"},
				"west": {"uv": [0, 0, 3, 16], "texture": "#0"},
				"up": {"uv": [0, 13, 16, 16], "rotation": 180, "texture": "#0"},
				"down": {"uv": [0, 13, 16, 16], "texture": "#0"}
			}
		},
		{
			"from": [0, 0, 13],
			"to": [16, 16, 16],
			"faces": {
				"north": {"uv": [0, 0, 16, 16], "texture": "#0"},
				"east": {"uv": [0, 0, 3, 16], "texture": "#0"},
				"south": {"uv": [0, 0, 16, 16], "texture": "#0"},
				"west": {"uv": [13, 0, 16, 16], "texture": "#0"},
				"up": {"uv": [0, 0, 16, 3], "rotation": 180, "texture": "#0"},
				"down": {"uv": [0, 0, 16, 3], "texture": "#0"}
			}
		},
		{
			"from": [0, 0, 3],
			"to": [3, 16, 13],
			"rotation": {"angle": 0, "axis": "y", "origin": [8, 8, 11]},
			"faces": {
				"north": {"uv": [0, 0, 0, 0], "texture": "#0"},
				"east": {"uv": [3, 0, 13, 16], "texture": "#0"},
				"south": {"uv": [0, 0, 0, 0], "texture": "#0"},
				"west": {"uv": [3, 0, 13, 16], "texture": "#0"},
				"up": {"uv": [13, 3, 16, 13], "rotation": 180, "texture": "#0"},
				"down": {"uv": [0, 3, 3, 13], "texture": "#0"}
			}
		},
		{
			"from": [13, 0, 3],
			"to": [16, 16, 13],
			"rotation": {"angle": 0, "axis": "y", "origin": [8, 8, 11]},
			"faces": {
				"north": {"uv": [0, 0, 0, 0], "texture": "#0"},
				"east": {"uv": [3, 0, 13, 16], "texture": "#0"},
				"south": {"uv": [0, 0, 0, 0], "texture": "#0"},
				"west": {"uv": [3, 0, 13, 16], "texture": "#0"},
				"up": {"uv": [0, 3, 3, 13], "rotation": 180, "texture": "#0"},
				"down": {"uv": [13, 3, 16, 13], "texture": "#0"}
			}
		}
	]
}